{
  "$schema": "https://biomejs.dev/schemas/1.9.0/schema.json",
  "files": {
    "ignore": ["**/dist/**", "**/.astro/**", "**/node_modules/**", "**/coverage/**", "**/playwright-report/**", "**/test-results/**", "**/pnpm-lock.yaml"]
  },
  "organizeImports": { "enabled": true },
  "linter": {
    "enabled": true,
    "rules": {
      "recommended": true,
      "correctness": { "noUnusedVariables": "error", "noUnusedImports": "error" },
      "style": { "noNonNullAssertion": "warn", "useConst": "error" },
      "suspicious": { "noExplicitAny": "warn" }
    }
  },
  "formatter": {
    "enabled": true,
    "indentStyle": "space",
    "indentWidth": 2,
    "lineWidth": 100
  },
  "javascript": { "formatter": { "quoteStyle": "single", "semicolons": "always" } }
}
